setup.py
ucsv/__init__.py
ucsv/ucsv.py
ucsv.egg-info/PKG-INFO
ucsv.egg-info/SOURCES.txt
ucsv.egg-info/dependency_links.txt
ucsv.egg-info/top_level.txt