Metadata-Version: 1.0
Name: ucsv
Version: 0.1
Summary: Unicode-aware replacement for Python-2.x CSV module
Home-page: https://github.com/pagepart/uscv
Author: PagePart Team
Author-email: opensource@pagepart.com
License: MIT
Platform: UNKNOWN
